{
  "project_info": {
    "project_number": "764070526715",
    "project_id": "bootcampdatabase-9b4d5",
    "storage_bucket": "bootcampdatabase-9b4d5.appspot.com"
  },
  "client": [
    {
      "client_info": {
        "mobilesdk_app_id": "1:764070526715:android:2863a09e464d24ba49fa5e",
        "android_client_info": {
          "package_name": "com.example.flutter_upgrde_app"
        }
      },
      "oauth_client": [],
      "api_key": [
        {
          "current_key": "AIzaSyAt1cGdIhOkX-Fkd83CadmFtHgm6mYgFYA"
        }
      ],
      "services": {
        "appinvite_service": {
          "other_platform_oauth_client": []
        }
      }
    }
  ],
  "configuration_version": "1"
}